restomatic/__init__.py
restomatic/endpoint.py
restomatic/json_sql_compositor.py
restomatic/shared_exceptions.py
restomatic/validations.py
restomatic/wsgi_debugger.py
restomatic/wsgi_endpoint_router.py
restomatic-0.3.1.dist-info/LICENSE
restomatic-0.3.1.dist-info/METADATA
restomatic-0.3.1.dist-info/WHEEL
restomatic-0.3.1.dist-info/top_level.txt
restomatic-0.3.1.dist-info/RECORD
