Metadata-Version: 2.1
Name: restomatic
Version: 0.3.1
Summary: Automatic JSON-based API generator, including a SQL Query Compositor and WSGI Endpoint Router
Home-page: https://github.com/dtulga/restomatic
Author: David Tulga
Author-email: davidtulga@gmail.com
License: MIT
Platform: UNKNOWN
Classifier: Programming Language :: Python :: 3
Classifier: License :: OSI Approved :: MIT License
Classifier: Operating System :: OS Independent
